README.txt
setup.py
importio_gsei/__init__.py
importio_gsei/extractor.py
importio_gsei/google.py
importio_gsei/main.py
importio_gsei/version.py
importio_gsei.egg-info/PKG-INFO
importio_gsei.egg-info/SOURCES.txt
importio_gsei.egg-info/dependency_links.txt
importio_gsei.egg-info/entry_points.txt
importio_gsei.egg-info/requires.txt
importio_gsei.egg-info/top_level.txt