Metadata-Version: 1.0
Name: importio-gsei
Version: 0.3.1
Summary: Command line to feed URLs from a Google Sheet into an Import.io Extractor
Home-page: http://github.io/import.io/google-sheets-extractor-integration
Author: David Gwartney
Author-email: david.gwartney@import.io
License: LICENSE
Platform: UNKNOWN
